obj_query/__init__.py
obj_query/ayx_data_map.py
obj_query/data_map.py
obj_query/query.py
obj_query-0.8.dist-info/LICENSE
obj_query-0.8.dist-info/METADATA
obj_query-0.8.dist-info/WHEEL
obj_query-0.8.dist-info/top_level.txt
obj_query-0.8.dist-info/RECORD
