Metadata-Version: 2.1
Name: obj-query
Version: 0.8
Summary: translate JSON and Python objects to Alteryx RecordInfos
Home-page: https://github.com/tlarsen7572/obj_query
Author: Thomas Larsen
Author-email: larsenthomasj@gmail.com
License: MIT
Platform: UNKNOWN
